hsipy/__init__.py
hsipy/hsi_visualization.py
hsipy/hsitools.py
hsipy-1.0.8.dist-info/METADATA
hsipy-1.0.8.dist-info/WHEEL
hsipy-1.0.8.dist-info/top_level.txt
hsipy-1.0.8.dist-info/RECORD
