Metadata-Version: 2.1
Name: hsipy
Version: 1.0.8
Summary: Python Module to do Hypespectral Imaging Analysis using the Phasor Transform
Home-page: https://github.com/schutyb
Author: Bruno Schuty Teske
Author-email: schutyb@schutyb.com
License: bsd-3-clause
Platform: UNKNOWN
